genelens/__init__.py
genelens/data/exampl_data/__init__.py
genelens/data/exampl_data/train_test.csv
genelens/data/exampl_data/validation.csv
genelens/data/miRNET/addData/.DS_Store
genelens/data/miRNET/addData/CADgens_DisGenNET.txt
genelens/data/miRNET/addData/GTEx_Analysis_2017-06-05_v8_RNASeQCv1.1.9_gene_median_tpm.gct
genelens/data/miRNET/addData/Hum_Atas_normal_tissue.tsv
genelens/data/miRNET/addData/__init__.py
genelens/data/miRNET/baseData/.DS_Store
genelens/data/miRNET/baseData/ReactomePathwaysRelation.txt
genelens/data/miRNET/baseData/String_interactome.csv
genelens/data/miRNET/baseData/__init__.py
genelens/data/miRNET/baseData/hsa_miRTarBase.csv
genelens/data/miRNET/baseData/mmu_String_interactome.csv
genelens/data/miRNET/baseData/mmu_miRTarBase.csv
genelens/enrichment.py
genelens/fselector.py
genelens/netanalyzer.py
genelens/options/.DS_Store
genelens/options/__init__.py
genelens/options/cytoscape_styles/PathwayEnrichStyles.json
genelens/options/cytoscape_styles/__init__.py
genelens/options/cytoscape_styles/miR_Net_Styles.json
genelens-0.1.11.dist-info/METADATA
genelens-0.1.11.dist-info/WHEEL
genelens-0.1.11.dist-info/RECORD
