Metadata-Version: 2.3
Name: GeneLens
Version: 0.1.11
Summary: Differential gene expression analysis via Monte-Carlo Machine Learning Inference and Network Analysis
Author: German
Author-email: german.osmak@gmail.com
Requires-Python: >=3.10,<4.0
Classifier: Programming Language :: Python :: 3
Classifier: Programming Language :: Python :: 3.10
Classifier: Programming Language :: Python :: 3.11
Classifier: Programming Language :: Python :: 3.12
Classifier: Programming Language :: Python :: 3.13
Requires-Dist: colour (>=0.1.5,<0.2.0)
Requires-Dist: jupyter (>=1.1.1,<2.0.0)
Requires-Dist: matplotlib (>=3.10.0,<4.0.0)
Requires-Dist: networkx (>=3.4.2,<4.0.0)
Requires-Dist: pandas (>=2.2.3,<3.0.0)
Requires-Dist: py2cytoscape (>=0.7.1,<0.8.0)
Requires-Dist: reactome2py (>=3.0.0,<4.0.0)
Requires-Dist: requests (>=2.32.3,<3.0.0)
Requires-Dist: scikit-learn (>=1.6.0,<2.0.0)
Requires-Dist: seaborn (>=0.13.2,<0.14.0)
Requires-Dist: tqdm (>=4.67.1,<5.0.0)
Project-URL: Documentation, https://gjosmak.github.io/GeneLens/
Project-URL: Repository, https://github.com/GJOsmak/GeneLens
